{
  "contents": [
    {
      "item_id": 100120001,
      "item_name": "포가튼 블레이드",
      "server_id": 116,
      "server_name": "아이린06",
      "enchant_level": 5,
      "grade": "legendary",
      "image": "https://wstatic-cdn.plaync.com/powerbook/l2m/icon/Icon_128/Item/Icon_WP_Sword_G2_002.png",
      "now_min_unit_price": 160000,
      "avg_unit_price": 0,
      "favorite": false
    },
    {
      "item_id": 100120001,
      "item_name": "포가튼 블레이드",
      "server_id": 122,
      "server_name": "오필리아02",
      "enchant_level": 7,
      "grade": "legendary",
      "image": "https://wstatic-cdn.plaync.com/powerbook/l2m/icon/Icon_128/Item/Icon_WP_Sword_G2_002.png",
      "now_min_unit_price": 170000,
      "avg_unit_price": 0,
      "favorite": false
    },
    {
      "item_id": 100120001,
      "item_name": "포가튼 블레이드",
      "server_id": 62,
      "server_name": "카스티엔02",
      "enchant_level": 7,
      "grade": "legendary",
      "image": "https://wstatic-cdn.plaync.com/powerbook/l2m/icon/Icon_128/Item/Icon_WP_Sword_G2_002.png",
      "now_min_unit_price": 170000,
      "avg_unit_price": 0,
      "favorite": false
    },
    {
      "item_id": 100120001,
      "item_name": "포가튼 블레이드",
      "server_id": 64,
      "server_name": "카스티엔04",
      "enchant_level": 7,
      "grade": "legendary",
      "image": "https://wstatic-cdn.plaync.com/powerbook/l2m/icon/Icon_128/Item/Icon_WP_Sword_G2_002.png",
      "now_min_unit_price": 170000,
      "avg_unit_price": 0,
      "favorite": false
    },
    {
      "item_id": 100120001,
      "item_name": "포가튼 블레이드",
      "server_id": 36,
      "server_name": "리오나06",
      "enchant_level": 7,
      "grade": "legendary",
      "image": "https://wstatic-cdn.plaync.com/powerbook/l2m/icon/Icon_128/Item/Icon_WP_Sword_G2_002.png",
      "now_min_unit_price": 175000,
      "avg_unit_price": 0,
      "favorite": false
    },
    {
      "item_id": 100120001,
      "item_name": "포가튼 블레이드",
      "server_id": 129,
      "server_name": "오필리아09",
      "enchant_level": 7,
      "grade": "legendary",
      "image": "https://wstatic-cdn.plaync.com/powerbook/l2m/icon/Icon_128/Item/Icon_WP_Sword_G2_002.png",
      "now_min_unit_price": 177000,
      "avg_unit_price": 0,
      "favorite": false
    },
    {
      "item_id": 100120001,
      "item_name": "포가튼 블레이드",
      "server_id": 82,
      "server_name": "드비안느02",
      "enchant_level": 7,
      "grade": "legendary",
      "image": "https://wstatic-cdn.plaync.com/powerbook/l2m/icon/Icon_128/Item/Icon_WP_Sword_G2_002.png",
      "now_min_unit_price": 183000,
      "avg_unit_price": 0,
      "favorite": false
    },
    {
      "item_id": 100120002,
      "item_name": "칼라드볼그",
      "server_id": 117,
      "server_name": "아이린07",
      "enchant_level": 0,
      "grade": "legendary",
      "image": "https://wstatic-cdn.plaync.com/powerbook/l2m/icon/Icon_128/Item/Icon_WP_Sword_G2_001.png",
      "now_min_unit_price": 78000,
      "avg_unit_price": 0,
      "favorite": false
    },
    {
      "item_id": 100120002,
      "item_name": "칼라드볼그",
      "server_id": 141,
      "server_name": "안타라스01",
      "enchant_level": 0,
      "grade": "legendary",
      "image": "https://wstatic-cdn.plaync.com/powerbook/l2m/icon/Icon_128/Item/Icon_WP_Sword_G2_001.png",
      "now_min_unit_price": 200000,
      "avg_unit_price": 0,
      "favorite": false
    },
    {
      "item_id": 100120002,
      "item_name": "칼라드볼그",
      "server_id": 150,
      "server_name": "안타라스10",
      "enchant_level": 7,
      "grade": "legendary",
      "image": "https://wstatic-cdn.plaync.com/powerbook/l2m/icon/Icon_128/Item/Icon_WP_Sword_G2_001.png",
      "now_min_unit_price": 220000,
      "avg_unit_price": 0,
      "favorite": false
    },
    {
      "item_id": 100220001,
      "item_name": "아스타로트",
      "server_id": 65,
      "server_name": "카스티엔05",
      "enchant_level": 7,
      "grade": "legendary",
      "image": "https://wstatic-cdn.plaync.com/powerbook/l2m/icon/Icon_128/Item/Icon_WP_DualWeapon_G2_001.png",
      "now_min_unit_price": 75000,
      "avg_unit_price": 0,
      "favorite": false
    },
    {
      "item_id": 100220001,
      "item_name": "아스타로트",
      "server_id": 131,
      "server_name": "바이움01",
      "enchant_level": 7,
      "grade": "legendary",
      "image": "https://wstatic-cdn.plaync.com/powerbook/l2m/icon/Icon_128/Item/Icon_WP_DualWeapon_G2_001.png",
      "now_min_unit_price": 75000,
      "avg_unit_price": 0,
      "favorite": false
    },
    {
      "item_id": 100220001,
      "item_name": "아스타로트",
      "server_id": 82,
      "server_name": "드비안느02",
      "enchant_level": 7,
      "grade": "legendary",
      "image": "https://wstatic-cdn.plaync.com/powerbook/l2m/icon/Icon_128/Item/Icon_WP_DualWeapon_G2_001.png",
      "now_min_unit_price": 88000,
      "avg_unit_price": 0,
      "favorite": false
    },
    {
      "item_id": 100220003,
      "item_name": "페리 엘",
      "server_id": 60,
      "server_name": "거스틴10",
      "enchant_level": 7,
      "grade": "legendary",
      "image": "https://wstatic-cdn.plaync.com/powerbook/l2m/icon/Icon_128/Item/Icon_WP_DualWeapon_G2_003.png",
      "now_min_unit_price": 155000,
      "avg_unit_price": 0,
      "favorite": false
    },
    {
      "item_id": 100320001,
      "item_name": "나가스톰",
      "server_id": 45,
      "server_name": "에리카05",
      "enchant_level": 0,
      "grade": "legendary",
      "image": "https://wstatic-cdn.plaync.com/powerbook/l2m/icon/Icon_128/Item/Icon_WP_Dagger_G2_001.png",
      "now_min_unit_price": 85000,
      "avg_unit_price": 0,
      "favorite": false
    }
  ],
  "pagination": {
    "page": 1,
    "size": 15,
    "last_page": 20697,
    "total": 310445
  }
}
{
  "contents": [
    {
      "item_id": 100320001,
      "item_name": "나가스톰",
      "server_id": 25,
      "server_name": "카인05",
      "enchant_level": 7,
      "grade": "legendary",
      "image": "https://wstatic-cdn.plaync.com/powerbook/l2m/icon/Icon_128/Item/Icon_WP_Dagger_G2_001.png",
      "now_min_unit_price": 85000,
      "avg_unit_price": 0,
      "favorite": false
    },
    {
      "item_id": 100320001,
      "item_name": "나가스톰",
      "server_id": 109,
      "server_name": "에르휘나09",
      "enchant_level": 7,
      "grade": "legendary",
      "image": "https://wstatic-cdn.plaync.com/powerbook/l2m/icon/Icon_128/Item/Icon_WP_Dagger_G2_001.png",
      "now_min_unit_price": 89000,
      "avg_unit_price": 0,
      "favorite": false
    },
    {
      "item_id": 100320001,
      "item_name": "나가스톰",
      "server_id": 130,
      "server_name": "오필리아10",
      "enchant_level": 7,
      "grade": "legendary",
      "image": "https://wstatic-cdn.plaync.com/powerbook/l2m/icon/Icon_128/Item/Icon_WP_Dagger_G2_001.png",
      "now_min_unit_price": 90000,
      "avg_unit_price": 0,
      "favorite": false
    },
    {
      "item_id": 100320001,
      "item_name": "나가스톰",
      "server_id": 45,
      "server_name": "에리카05",
      "enchant_level": 7,
      "grade": "legendary",
      "image": "https://wstatic-cdn.plaync.com/powerbook/l2m/icon/Icon_128/Item/Icon_WP_Dagger_G2_001.png",
      "now_min_unit_price": 90000,
      "avg_unit_price": 0,
      "favorite": false
    },
    {
      "item_id": 100320001,
      "item_name": "나가스톰",
      "server_id": 28,
      "server_name": "카인08",
      "enchant_level": 7,
      "grade": "legendary",
      "image": "https://wstatic-cdn.plaync.com/powerbook/l2m/icon/Icon_128/Item/Icon_WP_Dagger_G2_001.png",
      "now_min_unit_price": 120000,
      "avg_unit_price": 0,
      "favorite": false
    },
    {
      "item_id": 100320001,
      "item_name": "나가스톰",
      "server_id": 105,
      "server_name": "에르휘나05",
      "enchant_level": 8,
      "grade": "legendary",
      "image": "https://wstatic-cdn.plaync.com/powerbook/l2m/icon/Icon_128/Item/Icon_WP_Dagger_G2_001.png",
      "now_min_unit_price": 146000,
      "avg_unit_price": 0,
      "favorite": false
    },
    {
      "item_id": 100320003,
      "item_name": "다인슬라이프",
      "server_id": 91,
      "server_name": "테온01",
      "enchant_level": 0,
      "grade": "legendary",
      "image": "https://wstatic-cdn.plaync.com/powerbook/l2m/icon/Icon_128/Item/Icon_WP_Dagger_G2_003.png",
      "now_min_unit_price": 170000,
      "avg_unit_price": 0,
      "favorite": false
    },
    {
      "item_id": 100320003,
      "item_name": "다인슬라이프",
      "server_id": 30,
      "server_name": "카인10",
      "enchant_level": 0,
      "grade": "legendary",
      "image": "https://wstatic-cdn.plaync.com/powerbook/l2m/icon/Icon_128/Item/Icon_WP_Dagger_G2_003.png",
      "now_min_unit_price": 185000,
      "avg_unit_price": 0,
      "favorite": false
    },
    {
      "item_id": 100320003,
      "item_name": "다인슬라이프",
      "server_id": 59,
      "server_name": "거스틴09",
      "enchant_level": 7,
      "grade": "legendary",
      "image": "https://wstatic-cdn.plaync.com/powerbook/l2m/icon/Icon_128/Item/Icon_WP_Dagger_G2_003.png",
      "now_min_unit_price": 160000,
      "avg_unit_price": 0,
      "favorite": false
    },
    {
      "item_id": 100320003,
      "item_name": "다인슬라이프",
      "server_id": 127,
      "server_name": "오필리아07",
      "enchant_level": 7,
      "grade": "legendary",
      "image": "https://wstatic-cdn.plaync.com/powerbook/l2m/icon/Icon_128/Item/Icon_WP_Dagger_G2_003.png",
      "now_min_unit_price": 175000,
      "avg_unit_price": 0,
      "favorite": false
    },
    {
      "item_id": 100320003,
      "item_name": "다인슬라이프",
      "server_id": 73,
      "server_name": "아리아03",
      "enchant_level": 7,
      "grade": "legendary",
      "image": "https://wstatic-cdn.plaync.com/powerbook/l2m/icon/Icon_128/Item/Icon_WP_Dagger_G2_003.png",
      "now_min_unit_price": 199000,
      "avg_unit_price": 0,
      "favorite": false
    },
    {
      "item_id": 100320003,
      "item_name": "다인슬라이프",
      "server_id": 1,
      "server_name": "바츠01",
      "enchant_level": 7,
      "grade": "legendary",
      "image": "https://wstatic-cdn.plaync.com/powerbook/l2m/icon/Icon_128/Item/Icon_WP_Dagger_G2_003.png",
      "now_min_unit_price": 220000,
      "avg_unit_price": 0,
      "favorite": false
    },
    {
      "item_id": 100420001,
      "item_name": "드라코닉 보우",
      "server_id": 53,
      "server_name": "거스틴03",
      "enchant_level": 7,
      "grade": "legendary",
      "image": "https://wstatic-cdn.plaync.com/powerbook/l2m/icon/Icon_128/Item/Icon_WP_Bow_G2_002.png",
      "now_min_unit_price": 175000,
      "avg_unit_price": 0,
      "favorite": false
    },
    {
      "item_id": 100420001,
      "item_name": "드라코닉 보우",
      "server_id": 108,
      "server_name": "에르휘나08",
      "enchant_level": 7,
      "grade": "legendary",
      "image": "https://wstatic-cdn.plaync.com/powerbook/l2m/icon/Icon_128/Item/Icon_WP_Bow_G2_002.png",
      "now_min_unit_price": 190000,
      "avg_unit_price": 0,
      "favorite": false
    },
    {
      "item_id": 100420001,
      "item_name": "드라코닉 보우",
      "server_id": 24,
      "server_name": "카인04",
      "enchant_level": 7,
      "grade": "legendary",
      "image": "https://wstatic-cdn.plaync.com/powerbook/l2m/icon/Icon_128/Item/Icon_WP_Bow_G2_002.png",
      "now_min_unit_price": 210000,
      "avg_unit_price": 0,
      "favorite": false
    }
  ],
  "pagination": {
    "page": 2,
    "size": 15,
    "last_page": 20697,
    "total": 310445
  }
}
{
  "contents": [
    {
      "item_id": 100420001,
      "item_name": "드라코닉 보우",
      "server_id": 121,
      "server_name": "오필리아01",
      "enchant_level": 9,
      "grade": "legendary",
      "image": "https://wstatic-cdn.plaync.com/powerbook/l2m/icon/Icon_128/Item/Icon_WP_Bow_G2_002.png",
      "now_min_unit_price": 580000,
      "avg_unit_price": 0,
      "favorite": false
    },
    {
      "item_id": 100420002,
      "item_name": "샤이드 보우",
      "server_id": 14,
      "server_name": "지그하르트04",
      "enchant_level": 7,
      "grade": "legendary",
      "image": "https://wstatic-cdn.plaync.com/powerbook/l2m/icon/Icon_128/Item/Icon_WP_Bow_G2_001.png",
      "now_min_unit_price": 79000,
      "avg_unit_price": 0,
      "favorite": false
    },
    {
      "item_id": 100420002,
      "item_name": "샤이드 보우",
      "server_id": 76,
      "server_name": "아리아06",
      "enchant_level": 7,
      "grade": "legendary",
      "image": "https://wstatic-cdn.plaync.com/powerbook/l2m/icon/Icon_128/Item/Icon_WP_Bow_G2_001.png",
      "now_min_unit_price": 80000,
      "avg_unit_price": 0,
      "favorite": false
    },
    {
      "item_id": 100420002,
      "item_name": "샤이드 보우",
      "server_id": 30,
      "server_name": "카인10",
      "enchant_level": 7,
      "grade": "legendary",
      "image": "https://wstatic-cdn.plaync.com/powerbook/l2m/icon/Icon_128/Item/Icon_WP_Bow_G2_001.png",
      "now_min_unit_price": 81000,
      "avg_unit_price": 0,
      "favorite": false
    },
    {
      "item_id": 100420002,
      "item_name": "샤이드 보우",
      "server_id": 7,
      "server_name": "바츠07",
      "enchant_level": 7,
      "grade": "legendary",
      "image": "https://wstatic-cdn.plaync.com/powerbook/l2m/icon/Icon_128/Item/Icon_WP_Bow_G2_001.png",
      "now_min_unit_price": 82000,
      "avg_unit_price": 0,
      "favorite": false
    },
    {
      "item_id": 100420002,
      "item_name": "샤이드 보우",
      "server_id": 63,
      "server_name": "카스티엔03",
      "enchant_level": 7,
      "grade": "legendary",
      "image": "https://wstatic-cdn.plaync.com/powerbook/l2m/icon/Icon_128/Item/Icon_WP_Bow_G2_001.png",
      "now_min_unit_price": 86000,
      "avg_unit_price": 0,
      "favorite": false
    },
    {
      "item_id": 100420002,
      "item_name": "샤이드 보우",
      "server_id": 12,
      "server_name": "지그하르트02",
      "enchant_level": 7,
      "grade": "legendary",
      "image": "https://wstatic-cdn.plaync.com/powerbook/l2m/icon/Icon_128/Item/Icon_WP_Bow_G2_001.png",
      "now_min_unit_price": 88000,
      "avg_unit_price": 80000,
      "favorite": false
    },
    {
      "item_id": 100420002,
      "item_name": "샤이드 보우",
      "server_id": 127,
      "server_name": "오필리아07",
      "enchant_level": 7,
      "grade": "legendary",
      "image": "https://wstatic-cdn.plaync.com/powerbook/l2m/icon/Icon_128/Item/Icon_WP_Bow_G2_001.png",
      "now_min_unit_price": 96000,
      "avg_unit_price": 0,
      "favorite": false
    },
    {
      "item_id": 100420002,
      "item_name": "샤이드 보우",
      "server_id": 45,
      "server_name": "에리카05",
      "enchant_level": 7,
      "grade": "legendary",
      "image": "https://wstatic-cdn.plaync.com/powerbook/l2m/icon/Icon_128/Item/Icon_WP_Bow_G2_001.png",
      "now_min_unit_price": 100000,
      "avg_unit_price": 0,
      "favorite": false
    },
    {
      "item_id": 100420002,
      "item_name": "샤이드 보우",
      "server_id": 148,
      "server_name": "안타라스08",
      "enchant_level": 7,
      "grade": "legendary",
      "image": "https://wstatic-cdn.plaync.com/powerbook/l2m/icon/Icon_128/Item/Icon_WP_Bow_G2_001.png",
      "now_min_unit_price": 170000,
      "avg_unit_price": 0,
      "favorite": false
    },
    {
      "item_id": 100520001,
      "item_name": "임페리얼 스탭",
      "server_id": 55,
      "server_name": "거스틴05",
      "enchant_level": 0,
      "grade": "legendary",
      "image": "https://wstatic-cdn.plaync.com/powerbook/l2m/icon/Icon_128/Item/Icon_WP_Staff_G2_001.png",
      "now_min_unit_price": 77777,
      "avg_unit_price": 0,
      "favorite": false
    },
    {
      "item_id": 100520001,
      "item_name": "임페리얼 스탭",
      "server_id": 121,
      "server_name": "오필리아01",
      "enchant_level": 0,
      "grade": "legendary",
      "image": "https://wstatic-cdn.plaync.com/powerbook/l2m/icon/Icon_128/Item/Icon_WP_Staff_G2_001.png",
      "now_min_unit_price": 80000,
      "avg_unit_price": 0,
      "favorite": false
    },
    {
      "item_id": 100520001,
      "item_name": "임페리얼 스탭",
      "server_id": 21,
      "server_name": "카인01",
      "enchant_level": 0,
      "grade": "legendary",
      "image": "https://wstatic-cdn.plaync.com/powerbook/l2m/icon/Icon_128/Item/Icon_WP_Staff_G2_001.png",
      "now_min_unit_price": 80000,
      "avg_unit_price": 0,
      "favorite": false
    },
    {
      "item_id": 100520001,
      "item_name": "임페리얼 스탭",
      "server_id": 108,
      "server_name": "에르휘나08",
      "enchant_level": 7,
      "grade": "legendary",
      "image": "https://wstatic-cdn.plaync.com/powerbook/l2m/icon/Icon_128/Item/Icon_WP_Staff_G2_001.png",
      "now_min_unit_price": 72000,
      "avg_unit_price": 0,
      "favorite": false
    },
    {
      "item_id": 100520001,
      "item_name": "임페리얼 스탭",
      "server_id": 31,
      "server_name": "리오나01",
      "enchant_level": 7,
      "grade": "legendary",
      "image": "https://wstatic-cdn.plaync.com/powerbook/l2m/icon/Icon_128/Item/Icon_WP_Staff_G2_001.png",
      "now_min_unit_price": 74000,
      "avg_unit_price": 0,
      "favorite": false
    }
  ],
  "pagination": {
    "page": 3,
    "size": 15,
    "last_page": 20697,
    "total": 310444
  }
}
{
  "contents": [
    {
      "item_id": 100520001,
      "item_name": "임페리얼 스탭",
      "server_id": 81,
      "server_name": "드비안느01",
      "enchant_level": 7,
      "grade": "legendary",
      "image": "https://wstatic-cdn.plaync.com/powerbook/l2m/icon/Icon_128/Item/Icon_WP_Staff_G2_001.png",
      "now_min_unit_price": 75000,
      "avg_unit_price": 0,
      "favorite": false
    },
    {
      "item_id": 100520001,
      "item_name": "임페리얼 스탭",
      "server_id": 45,
      "server_name": "에리카05",
      "enchant_level": 7,
      "grade": "legendary",
      "image": "https://wstatic-cdn.plaync.com/powerbook/l2m/icon/Icon_128/Item/Icon_WP_Staff_G2_001.png",
      "now_min_unit_price": 75000,
      "avg_unit_price": 0,
      "favorite": false
    },
    {
      "item_id": 100520001,
      "item_name": "임페리얼 스탭",
      "server_id": 11,
      "server_name": "지그하르트01",
      "enchant_level": 7,
      "grade": "legendary",
      "image": "https://wstatic-cdn.plaync.com/powerbook/l2m/icon/Icon_128/Item/Icon_WP_Staff_G2_001.png",
      "now_min_unit_price": 79998,
      "avg_unit_price": 0,
      "favorite": false
    },
    {
      "item_id": 100520001,
      "item_name": "임페리얼 스탭",
      "server_id": 136,
      "server_name": "바이움06",
      "enchant_level": 7,
      "grade": "legendary",
      "image": "https://wstatic-cdn.plaync.com/powerbook/l2m/icon/Icon_128/Item/Icon_WP_Staff_G2_001.png",
      "now_min_unit_price": 80000,
      "avg_unit_price": 0,
      "favorite": false
    },
    {
      "item_id": 100520001,
      "item_name": "임페리얼 스탭",
      "server_id": 100,
      "server_name": "테온10",
      "enchant_level": 7,
      "grade": "legendary",
      "image": "https://wstatic-cdn.plaync.com/powerbook/l2m/icon/Icon_128/Item/Icon_WP_Staff_G2_001.png",
      "now_min_unit_price": 80000,
      "avg_unit_price": 0,
      "favorite": false
    },
    {
      "item_id": 100520001,
      "item_name": "임페리얼 스탭",
      "server_id": 76,
      "server_name": "아리아06",
      "enchant_level": 7,
      "grade": "legendary",
      "image": "https://wstatic-cdn.plaync.com/powerbook/l2m/icon/Icon_128/Item/Icon_WP_Staff_G2_001.png",
      "now_min_unit_price": 82000,
      "avg_unit_price": 0,
      "favorite": false
    },
    {
      "item_id": 100520001,
      "item_name": "임페리얼 스탭",
      "server_id": 70,
      "server_name": "카스티엔10",
      "enchant_level": 7,
      "grade": "legendary",
      "image": "https://wstatic-cdn.plaync.com/powerbook/l2m/icon/Icon_128/Item/Icon_WP_Staff_G2_001.png",
      "now_min_unit_price": 84500,
      "avg_unit_price": 0,
      "favorite": false
    },
    {
      "item_id": 100520001,
      "item_name": "임페리얼 스탭",
      "server_id": 84,
      "server_name": "드비안느04",
      "enchant_level": 7,
      "grade": "legendary",
      "image": "https://wstatic-cdn.plaync.com/powerbook/l2m/icon/Icon_128/Item/Icon_WP_Staff_G2_001.png",
      "now_min_unit_price": 85000,
      "avg_unit_price": 0,
      "favorite": false
    },
    {
      "item_id": 100520001,
      "item_name": "임페리얼 스탭",
      "server_id": 1,
      "server_name": "바츠01",
      "enchant_level": 7,
      "grade": "legendary",
      "image": "https://wstatic-cdn.plaync.com/powerbook/l2m/icon/Icon_128/Item/Icon_WP_Staff_G2_001.png",
      "now_min_unit_price": 90000,
      "avg_unit_price": 12000,
      "favorite": false
    },
    {
      "item_id": 100520001,
      "item_name": "임페리얼 스탭",
      "server_id": 132,
      "server_name": "바이움02",
      "enchant_level": 7,
      "grade": "legendary",
      "image": "https://wstatic-cdn.plaync.com/powerbook/l2m/icon/Icon_128/Item/Icon_WP_Staff_G2_001.png",
      "now_min_unit_price": 90000,
      "avg_unit_price": 0,
      "favorite": false
    },
    {
      "item_id": 100520003,
      "item_name": "아스트라페",
      "server_id": 122,
      "server_name": "오필리아02",
      "enchant_level": 0,
      "grade": "legendary",
      "image": "https://wstatic-cdn.plaync.com/powerbook/l2m/icon/Icon_128/Item/Icon_WP_Staff_G2_003.png",
      "now_min_unit_price": 180000,
      "avg_unit_price": 0,
      "favorite": false
    },
    {
      "item_id": 100520003,
      "item_name": "아스트라페",
      "server_id": 30,
      "server_name": "카인10",
      "enchant_level": 0,
      "grade": "legendary",
      "image": "https://wstatic-cdn.plaync.com/powerbook/l2m/icon/Icon_128/Item/Icon_WP_Staff_G2_003.png",
      "now_min_unit_price": 185000,
      "avg_unit_price": 0,
      "favorite": false
    },
    {
      "item_id": 100520003,
      "item_name": "아스트라페",
      "server_id": 36,
      "server_name": "리오나06",
      "enchant_level": 7,
      "grade": "legendary",
      "image": "https://wstatic-cdn.plaync.com/powerbook/l2m/icon/Icon_128/Item/Icon_WP_Staff_G2_003.png",
      "now_min_unit_price": 170000,
      "avg_unit_price": 0,
      "favorite": false
    },
    {
      "item_id": 100520003,
      "item_name": "아스트라페",
      "server_id": 56,
      "server_name": "거스틴06",
      "enchant_level": 7,
      "grade": "legendary",
      "image": "https://wstatic-cdn.plaync.com/powerbook/l2m/icon/Icon_128/Item/Icon_WP_Staff_G2_003.png",
      "now_min_unit_price": 185000,
      "avg_unit_price": 0,
      "favorite": false
    },
    {
      "item_id": 100620001,
      "item_name": "아르카나 오브",
      "server_id": 111,
      "server_name": "아이린01",
      "enchant_level": 0,
      "grade": "legendary",
      "image": "https://wstatic-cdn.plaync.com/powerbook/l2m/icon/Icon_128/Item/Icon_WP_Orb_G2_001.png",
      "now_min_unit_price": 80000,
      "avg_unit_price": 0,
      "favorite": false
    }
  ],
  "pagination": {
    "page": 4,
    "size": 15,
    "last_page": 20697,
    "total": 310444
  }
}
{
  "contents": [
    {
      "item_id": 100620001,
      "item_name": "아르카나 오브",
      "server_id": 21,
      "server_name": "카인01",
      "enchant_level": 5,
      "grade": "legendary",
      "image": "https://wstatic-cdn.plaync.com/powerbook/l2m/icon/Icon_128/Item/Icon_WP_Orb_G2_001.png",
      "now_min_unit_price": 78000,
      "avg_unit_price": 0,
      "favorite": false
    },
    {
      "item_id": 100620001,
      "item_name": "아르카나 오브",
      "server_id": 31,
      "server_name": "리오나01",
      "enchant_level": 5,
      "grade": "legendary",
      "image": "https://wstatic-cdn.plaync.com/powerbook/l2m/icon/Icon_128/Item/Icon_WP_Orb_G2_001.png",
      "now_min_unit_price": 85000,
      "avg_unit_price": 0,
      "favorite": false
    },
    {
      "item_id": 100620001,
      "item_name": "아르카나 오브",
      "server_id": 109,
      "server_name": "에르휘나09",
      "enchant_level": 7,
      "grade": "legendary",
      "image": "https://wstatic-cdn.plaync.com/powerbook/l2m/icon/Icon_128/Item/Icon_WP_Orb_G2_001.png",
      "now_min_unit_price": 75000,
      "avg_unit_price": 73000,
      "favorite": false
    },
    {
      "item_id": 100620001,
      "item_name": "아르카나 오브",
      "server_id": 98,
      "server_name": "테온08",
      "enchant_level": 7,
      "grade": "legendary",
      "image": "https://wstatic-cdn.plaync.com/powerbook/l2m/icon/Icon_128/Item/Icon_WP_Orb_G2_001.png",
      "now_min_unit_price": 80000,
      "avg_unit_price": 0,
      "favorite": false
    },
    {
      "item_id": 100620001,
      "item_name": "아르카나 오브",
      "server_id": 104,
      "server_name": "에르휘나04",
      "enchant_level": 7,
      "grade": "legendary",
      "image": "https://wstatic-cdn.plaync.com/powerbook/l2m/icon/Icon_128/Item/Icon_WP_Orb_G2_001.png",
      "now_min_unit_price": 80000,
      "avg_unit_price": 0,
      "favorite": false
    },
    {
      "item_id": 100620001,
      "item_name": "아르카나 오브",
      "server_id": 12,
      "server_name": "지그하르트02",
      "enchant_level": 7,
      "grade": "legendary",
      "image": "https://wstatic-cdn.plaync.com/powerbook/l2m/icon/Icon_128/Item/Icon_WP_Orb_G2_001.png",
      "now_min_unit_price": 85000,
      "avg_unit_price": 82000,
      "favorite": false
    },
    {
      "item_id": 100620001,
      "item_name": "아르카나 오브",
      "server_id": 82,
      "server_name": "드비안느02",
      "enchant_level": 7,
      "grade": "legendary",
      "image": "https://wstatic-cdn.plaync.com/powerbook/l2m/icon/Icon_128/Item/Icon_WP_Orb_G2_001.png",
      "now_min_unit_price": 85000,
      "avg_unit_price": 0,
      "favorite": false
    },
    {
      "item_id": 100620001,
      "item_name": "아르카나 오브",
      "server_id": 24,
      "server_name": "카인04",
      "enchant_level": 7,
      "grade": "legendary",
      "image": "https://wstatic-cdn.plaync.com/powerbook/l2m/icon/Icon_128/Item/Icon_WP_Orb_G2_001.png",
      "now_min_unit_price": 90000,
      "avg_unit_price": 0,
      "favorite": false
    },
    {
      "item_id": 100620001,
      "item_name": "아르카나 오브",
      "server_id": 10,
      "server_name": "바츠10",
      "enchant_level": 7,
      "grade": "legendary",
      "image": "https://wstatic-cdn.plaync.com/powerbook/l2m/icon/Icon_128/Item/Icon_WP_Orb_G2_001.png",
      "now_min_unit_price": 90000,
      "avg_unit_price": 0,
      "favorite": false
    },
    {
      "item_id": 100620001,
      "item_name": "아르카나 오브",
      "server_id": 96,
      "server_name": "테온06",
      "enchant_level": 7,
      "grade": "legendary",
      "image": "https://wstatic-cdn.plaync.com/powerbook/l2m/icon/Icon_128/Item/Icon_WP_Orb_G2_001.png",
      "now_min_unit_price": 90000,
      "avg_unit_price": 0,
      "favorite": false
    },
    {
      "item_id": 100620001,
      "item_name": "아르카나 오브",
      "server_id": 6,
      "server_name": "바츠06",
      "enchant_level": 7,
      "grade": "legendary",
      "image": "https://wstatic-cdn.plaync.com/powerbook/l2m/icon/Icon_128/Item/Icon_WP_Orb_G2_001.png",
      "now_min_unit_price": 90000,
      "avg_unit_price": 90000,
      "favorite": false
    },
    {
      "item_id": 100620001,
      "item_name": "아르카나 오브",
      "server_id": 146,
      "server_name": "안타라스06",
      "enchant_level": 7,
      "grade": "legendary",
      "image": "https://wstatic-cdn.plaync.com/powerbook/l2m/icon/Icon_128/Item/Icon_WP_Orb_G2_001.png",
      "now_min_unit_price": 150000,
      "avg_unit_price": 0,
      "favorite": false
    },
    {
      "item_id": 100620001,
      "item_name": "아르카나 오브",
      "server_id": 85,
      "server_name": "드비안느05",
      "enchant_level": 9,
      "grade": "legendary",
      "image": "https://wstatic-cdn.plaync.com/powerbook/l2m/icon/Icon_128/Item/Icon_WP_Orb_G2_001.png",
      "now_min_unit_price": 240000,
      "avg_unit_price": 0,
      "favorite": false
    },
    {
      "item_id": 100620003,
      "item_name": "세이크리디움",
      "server_id": 131,
      "server_name": "바이움01",
      "enchant_level": 0,
      "grade": "legendary",
      "image": "https://wstatic-cdn.plaync.com/powerbook/l2m/icon/Icon_128/Item/Icon_WP_Orb_G2_003.png",
      "now_min_unit_price": 148000,
      "avg_unit_price": 0,
      "favorite": false
    },
    {
      "item_id": 100620003,
      "item_name": "세이크리디움",
      "server_id": 64,
      "server_name": "카스티엔04",
      "enchant_level": 0,
      "grade": "legendary",
      "image": "https://wstatic-cdn.plaync.com/powerbook/l2m/icon/Icon_128/Item/Icon_WP_Orb_G2_003.png",
      "now_min_unit_price": 160000,
      "avg_unit_price": 0,
      "favorite": false
    }
  ],
  "pagination": {
    "page": 5,
    "size": 15,
    "last_page": 20697,
    "total": 310444
  }
}
{
  "contents": [
    {
      "item_id": 100620003,
      "item_name": "세이크리디움",
      "server_id": 109,
      "server_name": "에르휘나09",
      "enchant_level": 7,
      "grade": "legendary",
      "image": "https://wstatic-cdn.plaync.com/powerbook/l2m/icon/Icon_128/Item/Icon_WP_Orb_G2_003.png",
      "now_min_unit_price": 149000,
      "avg_unit_price": 0,
      "favorite": false
    },
    {
      "item_id": 100620003,
      "item_name": "세이크리디움",
      "server_id": 11,
      "server_name": "지그하르트01",
      "enchant_level": 7,
      "grade": "legendary",
      "image": "https://wstatic-cdn.plaync.com/powerbook/l2m/icon/Icon_128/Item/Icon_WP_Orb_G2_003.png",
      "now_min_unit_price": 155000,
      "avg_unit_price": 0,
      "favorite": false
    },
    {
      "item_id": 100720001,
      "item_name": "세인트 스피어",
      "server_id": 22,
      "server_name": "카인02",
      "enchant_level": 0,
      "grade": "legendary",
      "image": "https://wstatic-cdn.plaync.com/powerbook/l2m/icon/Icon_128/Item/Icon_WP_Spear_G2_001.png",
      "now_min_unit_price": 75000,
      "avg_unit_price": 0,
      "favorite": false
    },
    {
      "item_id": 100720001,
      "item_name": "세인트 스피어",
      "server_id": 34,
      "server_name": "리오나04",
      "enchant_level": 0,
      "grade": "legendary",
      "image": "https://wstatic-cdn.plaync.com/powerbook/l2m/icon/Icon_128/Item/Icon_WP_Spear_G2_001.png",
      "now_min_unit_price": 80000,
      "avg_unit_price": 0,
      "favorite": false
    },
    {
      "item_id": 100720001,
      "item_name": "세인트 스피어",
      "server_id": 142,
      "server_name": "안타라스02",
      "enchant_level": 0,
      "grade": "legendary",
      "image": "https://wstatic-cdn.plaync.com/powerbook/l2m/icon/Icon_128/Item/Icon_WP_Spear_G2_001.png",
      "now_min_unit_price": 149500,
      "avg_unit_price": 0,
      "favorite": false
    },
    {
      "item_id": 100720001,
      "item_name": "세인트 스피어",
      "server_id": 116,
      "server_name": "아이린06",
      "enchant_level": 7,
      "grade": "legendary",
      "image": "https://wstatic-cdn.plaync.com/powerbook/l2m/icon/Icon_128/Item/Icon_WP_Spear_G2_001.png",
      "now_min_unit_price": 75000,
      "avg_unit_price": 0,
      "favorite": false
    },
    {
      "item_id": 100720001,
      "item_name": "세인트 스피어",
      "server_id": 105,
      "server_name": "에르휘나05",
      "enchant_level": 7,
      "grade": "legendary",
      "image": "https://wstatic-cdn.plaync.com/powerbook/l2m/icon/Icon_128/Item/Icon_WP_Spear_G2_001.png",
      "now_min_unit_price": 77777,
      "avg_unit_price": 0,
      "favorite": false
    },
    {
      "item_id": 100720001,
      "item_name": "세인트 스피어",
      "server_id": 99,
      "server_name": "테온09",
      "enchant_level": 7,
      "grade": "legendary",
      "image": "https://wstatic-cdn.plaync.com/powerbook/l2m/icon/Icon_128/Item/Icon_WP_Spear_G2_001.png",
      "now_min_unit_price": 80000,
      "avg_unit_price": 80000,
      "favorite": false
    },
    {
      "item_id": 100720001,
      "item_name": "세인트 스피어",
      "server_id": 91,
      "server_name": "테온01",
      "enchant_level": 7,
      "grade": "legendary",
      "image": "https://wstatic-cdn.plaync.com/powerbook/l2m/icon/Icon_128/Item/Icon_WP_Spear_G2_001.png",
      "now_min_unit_price": 89000,
      "avg_unit_price": 0,
      "favorite": false
    },
    {
      "item_id": 100720002,
      "item_name": "타이폰 스피어",
      "server_id": 11,
      "server_name": "지그하르트01",
      "enchant_level": 0,
      "grade": "legendary",
      "image": "https://wstatic-cdn.plaync.com/powerbook/l2m/icon/Icon_128/Item/Icon_WP_Spear_G2_002.png",
      "now_min_unit_price": 170000,
      "avg_unit_price": 0,
      "favorite": false
    },
    {
      "item_id": 100720002,
      "item_name": "타이폰 스피어",
      "server_id": 38,
      "server_name": "리오나08",
      "enchant_level": 7,
      "grade": "legendary",
      "image": "https://wstatic-cdn.plaync.com/powerbook/l2m/icon/Icon_128/Item/Icon_WP_Spear_G2_002.png",
      "now_min_unit_price": 150000,
      "avg_unit_price": 0,
      "favorite": false
    },
    {
      "item_id": 100920001,
      "item_name": "페더아이 버스터",
      "server_id": 45,
      "server_name": "에리카05",
      "enchant_level": 0,
      "grade": "legendary",
      "image": "https://wstatic-cdn.plaync.com/powerbook/l2m/icon/Icon_128/Item/Icon_WP_GreatSword_G2_001.png",
      "now_min_unit_price": 80000,
      "avg_unit_price": 90000,
      "favorite": false
    },
    {
      "item_id": 100920001,
      "item_name": "페더아이 버스터",
      "server_id": 22,
      "server_name": "카인02",
      "enchant_level": 0,
      "grade": "legendary",
      "image": "https://wstatic-cdn.plaync.com/powerbook/l2m/icon/Icon_128/Item/Icon_WP_GreatSword_G2_001.png",
      "now_min_unit_price": 82000,
      "avg_unit_price": 0,
      "favorite": false
    },
    {
      "item_id": 100920001,
      "item_name": "페더아이 버스터",
      "server_id": 148,
      "server_name": "안타라스08",
      "enchant_level": 0,
      "grade": "legendary",
      "image": "https://wstatic-cdn.plaync.com/powerbook/l2m/icon/Icon_128/Item/Icon_WP_GreatSword_G2_001.png",
      "now_min_unit_price": 250000,
      "avg_unit_price": 0,
      "favorite": false
    },
    {
      "item_id": 100920001,
      "item_name": "페더아이 버스터",
      "server_id": 99,
      "server_name": "테온09",
      "enchant_level": 5,
      "grade": "legendary",
      "image": "https://wstatic-cdn.plaync.com/powerbook/l2m/icon/Icon_128/Item/Icon_WP_GreatSword_G2_001.png",
      "now_min_unit_price": 80000,
      "avg_unit_price": 0,
      "favorite": false
    }
  ],
  "pagination": {
    "page": 6,
    "size": 15,
    "last_page": 20697,
    "total": 310444
  }
}
{
  "contents": [
    {
      "item_id": 100920001,
      "item_name": "페더아이 버스터",
      "server_id": 1,
      "server_name": "바츠01",
      "enchant_level": 5,
      "grade": "legendary",
      "image": "https://wstatic-cdn.plaync.com/powerbook/l2m/icon/Icon_128/Item/Icon_WP_GreatSword_G2_001.png",
      "now_min_unit_price": 85000,
      "avg_unit_price": 0,
      "favorite": false
    },
    {
      "item_id": 100920001,
      "item_name": "페더아이 버스터",
      "server_id": 106,
      "server_name": "에르휘나06",
      "enchant_level": 6,
      "grade": "legendary",
      "image": "https://wstatic-cdn.plaync.com/powerbook/l2m/icon/Icon_128/Item/Icon_WP_GreatSword_G2_001.png",
      "now_min_unit_price": 84000,
      "avg_unit_price": 0,
      "favorite": false
    },
    {
      "item_id": 100920001,
      "item_name": "페더아이 버스터",
      "server_id": 72,
      "server_name": "아리아02",
      "enchant_level": 7,
      "grade": "legendary",
      "image": "https://wstatic-cdn.plaync.com/powerbook/l2m/icon/Icon_128/Item/Icon_WP_GreatSword_G2_001.png",
      "now_min_unit_price": 79000,
      "avg_unit_price": 80000,
      "favorite": false
    },
    {
      "item_id": 100920001,
      "item_name": "페더아이 버스터",
      "server_id": 11,
      "server_name": "지그하르트01",
      "enchant_level": 7,
      "grade": "legendary",
      "image": "https://wstatic-cdn.plaync.com/powerbook/l2m/icon/Icon_128/Item/Icon_WP_GreatSword_G2_001.png",
      "now_min_unit_price": 79998,
      "avg_unit_price": 84450,
      "favorite": false
    },
    {
      "item_id": 100920001,
      "item_name": "페더아이 버스터",
      "server_id": 4,
      "server_name": "바츠04",
      "enchant_level": 7,
      "grade": "legendary",
      "image": "https://wstatic-cdn.plaync.com/powerbook/l2m/icon/Icon_128/Item/Icon_WP_GreatSword_G2_001.png",
      "now_min_unit_price": 82000,
      "avg_unit_price": 0,
      "favorite": false
    },
    {
      "item_id": 100920001,
      "item_name": "페더아이 버스터",
      "server_id": 85,
      "server_name": "드비안느05",
      "enchant_level": 7,
      "grade": "legendary",
      "image": "https://wstatic-cdn.plaync.com/powerbook/l2m/icon/Icon_128/Item/Icon_WP_GreatSword_G2_001.png",
      "now_min_unit_price": 82000,
      "avg_unit_price": 88000,
      "favorite": false
    },
    {
      "item_id": 100920001,
      "item_name": "페더아이 버스터",
      "server_id": 99,
      "server_name": "테온09",
      "enchant_level": 7,
      "grade": "legendary",
      "image": "https://wstatic-cdn.plaync.com/powerbook/l2m/icon/Icon_128/Item/Icon_WP_GreatSword_G2_001.png",
      "now_min_unit_price": 82000,
      "avg_unit_price": 79000,
      "favorite": false
    },
    {
      "item_id": 100920001,
      "item_name": "페더아이 버스터",
      "server_id": 68,
      "server_name": "카스티엔08",
      "enchant_level": 7,
      "grade": "legendary",
      "image": "https://wstatic-cdn.plaync.com/powerbook/l2m/icon/Icon_128/Item/Icon_WP_GreatSword_G2_001.png",
      "now_min_unit_price": 83000,
      "avg_unit_price": 85000,
      "favorite": false
    },
    {
      "item_id": 100920001,
      "item_name": "페더아이 버스터",
      "server_id": 74,
      "server_name": "아리아04",
      "enchant_level": 7,
      "grade": "legendary",
      "image": "https://wstatic-cdn.plaync.com/powerbook/l2m/icon/Icon_128/Item/Icon_WP_GreatSword_G2_001.png",
      "now_min_unit_price": 85000,
      "avg_unit_price": 77000,
      "favorite": false
    },
    {
      "item_id": 100920001,
      "item_name": "페더아이 버스터",
      "server_id": 50,
      "server_name": "에리카10",
      "enchant_level": 7,
      "grade": "legendary",
      "image": "https://wstatic-cdn.plaync.com/powerbook/l2m/icon/Icon_128/Item/Icon_WP_GreatSword_G2_001.png",
      "now_min_unit_price": 88000,
      "avg_unit_price": 0,
      "favorite": false
    },
    {
      "item_id": 100920001,
      "item_name": "페더아이 버스터",
      "server_id": 89,
      "server_name": "드비안느09",
      "enchant_level": 7,
      "grade": "legendary",
      "image": "https://wstatic-cdn.plaync.com/powerbook/l2m/icon/Icon_128/Item/Icon_WP_GreatSword_G2_001.png",
      "now_min_unit_price": 89000,
      "avg_unit_price": 0,
      "favorite": false
    },
    {
      "item_id": 100920001,
      "item_name": "페더아이 버스터",
      "server_id": 1,
      "server_name": "바츠01",
      "enchant_level": 7,
      "grade": "legendary",
      "image": "https://wstatic-cdn.plaync.com/powerbook/l2m/icon/Icon_128/Item/Icon_WP_GreatSword_G2_001.png",
      "now_min_unit_price": 90000,
      "avg_unit_price": 0,
      "favorite": false
    },
    {
      "item_id": 100920001,
      "item_name": "페더아이 버스터",
      "server_id": 48,
      "server_name": "에리카08",
      "enchant_level": 7,
      "grade": "legendary",
      "image": "https://wstatic-cdn.plaync.com/powerbook/l2m/icon/Icon_128/Item/Icon_WP_GreatSword_G2_001.png",
      "now_min_unit_price": 90000,
      "avg_unit_price": 76000,
      "favorite": false
    },
    {
      "item_id": 100920001,
      "item_name": "페더아이 버스터",
      "server_id": 69,
      "server_name": "카스티엔09",
      "enchant_level": 7,
      "grade": "legendary",
      "image": "https://wstatic-cdn.plaync.com/powerbook/l2m/icon/Icon_128/Item/Icon_WP_GreatSword_G2_001.png",
      "now_min_unit_price": 95000,
      "avg_unit_price": 0,
      "favorite": false
    },
    {
      "item_id": 100920001,
      "item_name": "페더아이 버스터",
      "server_id": 109,
      "server_name": "에르휘나09",
      "enchant_level": 7,
      "grade": "legendary",
      "image": "https://wstatic-cdn.plaync.com/powerbook/l2m/icon/Icon_128/Item/Icon_WP_GreatSword_G2_001.png",
      "now_min_unit_price": 100000,
      "avg_unit_price": 0,
      "favorite": false
    }
  ],
  "pagination": {
    "page": 7,
    "size": 15,
    "last_page": 20697,
    "total": 310444
  }
}
{
  "contents": [
    {
      "item_id": 100920001,
      "item_name": "페더아이 버스터",
      "server_id": 149,
      "server_name": "안타라스09",
      "enchant_level": 7,
      "grade": "legendary",
      "image": "https://wstatic-cdn.plaync.com/powerbook/l2m/icon/Icon_128/Item/Icon_WP_GreatSword_G2_001.png",
      "now_min_unit_price": 250000,
      "avg_unit_price": 0,
      "favorite": false
    },
    {
      "item_id": 100920002,
      "item_name": "라바몬드 쏘우",
      "server_id": 11,
      "server_name": "지그하르트01",
      "enchant_level": 0,
      "grade": "legendary",
      "image": "https://wstatic-cdn.plaync.com/powerbook/l2m/icon/Icon_128/Item/Icon_WP_GreatSword_G2_002.png",
      "now_min_unit_price": 170000,
      "avg_unit_price": 0,
      "favorite": false
    },
    {
      "item_id": 100920002,
      "item_name": "라바몬드 쏘우",
      "server_id": 39,
      "server_name": "리오나09",
      "enchant_level": 7,
      "grade": "legendary",
      "image": "https://wstatic-cdn.plaync.com/powerbook/l2m/icon/Icon_128/Item/Icon_WP_GreatSword_G2_002.png",
      "now_min_unit_price": 169000,
      "avg_unit_price": 0,
      "favorite": false
    },
    {
      "item_id": 200120001,
      "item_name": "임페리얼 크루세이더 흉갑",
      "server_id": 8,
      "server_name": "바츠08",
      "enchant_level": 5,
      "grade": "legendary",
      "image": "https://wstatic-cdn.plaync.com/powerbook/l2m/icon/Icon_128/Item/Icon_AR_Torso_G2_003.png",
      "now_min_unit_price": 63000,
      "avg_unit_price": 0,
      "favorite": false
    },
    {
      "item_id": 200120001,
      "item_name": "임페리얼 크루세이더 흉갑",
      "server_id": 122,
      "server_name": "오필리아02",
      "enchant_level": 5,
      "grade": "legendary",
      "image": "https://wstatic-cdn.plaync.com/powerbook/l2m/icon/Icon_128/Item/Icon_AR_Torso_G2_003.png",
      "now_min_unit_price": 78000,
      "avg_unit_price": 0,
      "favorite": false
    },
    {
      "item_id": 200120001,
      "item_name": "임페리얼 크루세이더 흉갑",
      "server_id": 96,
      "server_name": "테온06",
      "enchant_level": 5,
      "grade": "legendary",
      "image": "https://wstatic-cdn.plaync.com/powerbook/l2m/icon/Icon_128/Item/Icon_AR_Torso_G2_003.png",
      "now_min_unit_price": 83000,
      "avg_unit_price": 0,
      "favorite": false
    },
    {
      "item_id": 200120001,
      "item_name": "임페리얼 크루세이더 흉갑",
      "server_id": 92,
      "server_name": "테온02",
      "enchant_level": 5,
      "grade": "legendary",
      "image": "https://wstatic-cdn.plaync.com/powerbook/l2m/icon/Icon_128/Item/Icon_AR_Torso_G2_003.png",
      "now_min_unit_price": 85000,
      "avg_unit_price": 0,
      "favorite": false
    },
    {
      "item_id": 200120001,
      "item_name": "임페리얼 크루세이더 흉갑",
      "server_id": 62,
      "server_name": "카스티엔02",
      "enchant_level": 5,
      "grade": "legendary",
      "image": "https://wstatic-cdn.plaync.com/powerbook/l2m/icon/Icon_128/Item/Icon_AR_Torso_G2_003.png",
      "now_min_unit_price": 95000,
      "avg_unit_price": 0,
      "favorite": false
    },
    {
      "item_id": 200120002,
      "item_name": "메이저 아르카나 로브",
      "server_id": 132,
      "server_name": "바이움02",
      "enchant_level": 5,
      "grade": "legendary",
      "image": "https://wstatic-cdn.plaync.com/powerbook/l2m/icon/Icon_128/Item/Icon_AR_Torso_G2_002.png",
      "now_min_unit_price": 60000,
      "avg_unit_price": 0,
      "favorite": false
    },
    {
      "item_id": 200120002,
      "item_name": "메이저 아르카나 로브",
      "server_id": 35,
      "server_name": "리오나05",
      "enchant_level": 5,
      "grade": "legendary",
      "image": "https://wstatic-cdn.plaync.com/powerbook/l2m/icon/Icon_128/Item/Icon_AR_Torso_G2_002.png",
      "now_min_unit_price": 65000,
      "avg_unit_price": 85000,
      "favorite": false
    },
    {
      "item_id": 200120002,
      "item_name": "메이저 아르카나 로브",
      "server_id": 12,
      "server_name": "지그하르트02",
      "enchant_level": 5,
      "grade": "legendary",
      "image": "https://wstatic-cdn.plaync.com/powerbook/l2m/icon/Icon_128/Item/Icon_AR_Torso_G2_002.png",
      "now_min_unit_price": 68000,
      "avg_unit_price": 0,
      "favorite": false
    },
    {
      "item_id": 200120002,
      "item_name": "메이저 아르카나 로브",
      "server_id": 45,
      "server_name": "에리카05",
      "enchant_level": 5,
      "grade": "legendary",
      "image": "https://wstatic-cdn.plaync.com/powerbook/l2m/icon/Icon_128/Item/Icon_AR_Torso_G2_002.png",
      "now_min_unit_price": 85000,
      "avg_unit_price": 0,
      "favorite": false
    },
    {
      "item_id": 200120002,
      "item_name": "메이저 아르카나 로브",
      "server_id": 141,
      "server_name": "안타라스01",
      "enchant_level": 5,
      "grade": "legendary",
      "image": "https://wstatic-cdn.plaync.com/powerbook/l2m/icon/Icon_128/Item/Icon_AR_Torso_G2_002.png",
      "now_min_unit_price": 180000,
      "avg_unit_price": 0,
      "favorite": false
    },
    {
      "item_id": 200120003,
      "item_name": "드라코닉 레더 아머",
      "server_id": 30,
      "server_name": "카인10",
      "enchant_level": 5,
      "grade": "legendary",
      "image": "https://wstatic-cdn.plaync.com/powerbook/l2m/icon/Icon_128/Item/Icon_AR_Torso_G2_001.png",
      "now_min_unit_price": 65000,
      "avg_unit_price": 0,
      "favorite": false
    },
    {
      "item_id": 200120003,
      "item_name": "드라코닉 레더 아머",
      "server_id": 13,
      "server_name": "지그하르트03",
      "enchant_level": 5,
      "grade": "legendary",
      "image": "https://wstatic-cdn.plaync.com/powerbook/l2m/icon/Icon_128/Item/Icon_AR_Torso_G2_001.png",
      "now_min_unit_price": 70000,
      "avg_unit_price": 0,
      "favorite": false
    }
  ],
  "pagination": {
    "page": 8,
    "size": 15,
    "last_page": 20697,
    "total": 310443
  }
}
{
  "contents": [
    {
      "item_id": 200120003,
      "item_name": "드라코닉 레더 아머",
      "server_id": 110,
      "server_name": "에르휘나10",
      "enchant_level": 5,
      "grade": "legendary",
      "image": "https://wstatic-cdn.plaync.com/powerbook/l2m/icon/Icon_128/Item/Icon_AR_Torso_G2_001.png",
      "now_min_unit_price": 75000,
      "avg_unit_price": 0,
      "favorite": false
    },
    {
      "item_id": 200120003,
      "item_name": "드라코닉 레더 아머",
      "server_id": 108,
      "server_name": "에르휘나08",
      "enchant_level": 5,
      "grade": "legendary",
      "image": "https://wstatic-cdn.plaync.com/powerbook/l2m/icon/Icon_128/Item/Icon_AR_Torso_G2_001.png",
      "now_min_unit_price": 95000,
      "avg_unit_price": 0,
      "favorite": false
    },
    {
      "item_id": 200120004,
      "item_name": "타락 천사의 흉갑",
      "server_id": 91,
      "server_name": "테온01",
      "enchant_level": 5,
      "grade": "legendary",
      "image": "https://wstatic-cdn.plaync.com/powerbook/l2m/icon/Icon_128/Item/Icon_AR_Torso_G2_004.png",
      "now_min_unit_price": 175000,
      "avg_unit_price": 0,
      "favorite": false
    },
    {
      "item_id": 200120004,
      "item_name": "타락 천사의 흉갑",
      "server_id": 109,
      "server_name": "에르휘나09",
      "enchant_level": 5,
      "grade": "legendary",
      "image": "https://wstatic-cdn.plaync.com/powerbook/l2m/icon/Icon_128/Item/Icon_AR_Torso_G2_004.png",
      "now_min_unit_price": 175000,
      "avg_unit_price": 170000,
      "favorite": false
    },
    {
      "item_id": 200120004,
      "item_name": "타락 천사의 흉갑",
      "server_id": 72,
      "server_name": "아리아02",
      "enchant_level": 5,
      "grade": "legendary",
      "image": "https://wstatic-cdn.plaync.com/powerbook/l2m/icon/Icon_128/Item/Icon_AR_Torso_G2_004.png",
      "now_min_unit_price": 175000,
      "avg_unit_price": 0,
      "favorite": false
    },
    {
      "item_id": 200120004,
      "item_name": "타락 천사의 흉갑",
      "server_id": 35,
      "server_name": "리오나05",
      "enchant_level": 5,
      "grade": "legendary",
      "image": "https://wstatic-cdn.plaync.com/powerbook/l2m/icon/Icon_128/Item/Icon_AR_Torso_G2_004.png",
      "now_min_unit_price": 185000,
      "avg_unit_price": 170000,
      "favorite": false
    },
    {
      "item_id": 200220001,
      "item_name": "임페리얼 크루세이더 각반",
      "server_id": 131,
      "server_name": "바이움01",
      "enchant_level": 0,
      "grade": "legendary",
      "image": "https://wstatic-cdn.plaync.com/powerbook/l2m/icon/Icon_128/Item/Icon_AR_Pants_G2_001.png",
      "now_min_unit_price": 58000,
      "avg_unit_price": 0,
      "favorite": false
    },
    {
      "item_id": 200220001,
      "item_name": "임페리얼 크루세이더 각반",
      "server_id": 143,
      "server_name": "안타라스03",
      "enchant_level": 0,
      "grade": "legendary",
      "image": "https://wstatic-cdn.plaync.com/powerbook/l2m/icon/Icon_128/Item/Icon_AR_Pants_G2_001.png",
      "now_min_unit_price": 120000,
      "avg_unit_price": 0,
      "favorite": false
    },
    {
      "item_id": 200220001,
      "item_name": "임페리얼 크루세이더 각반",
      "server_id": 132,
      "server_name": "바이움02",
      "enchant_level": 5,
      "grade": "legendary",
      "image": "https://wstatic-cdn.plaync.com/powerbook/l2m/icon/Icon_128/Item/Icon_AR_Pants_G2_001.png",
      "now_min_unit_price": 58000,
      "avg_unit_price": 0,
      "favorite": false
    },
    {
      "item_id": 200220001,
      "item_name": "임페리얼 크루세이더 각반",
      "server_id": 85,
      "server_name": "드비안느05",
      "enchant_level": 5,
      "grade": "legendary",
      "image": "https://wstatic-cdn.plaync.com/powerbook/l2m/icon/Icon_128/Item/Icon_AR_Pants_G2_001.png",
      "now_min_unit_price": 60000,
      "avg_unit_price": 0,
      "favorite": false
    },
    {
      "item_id": 200220001,
      "item_name": "임페리얼 크루세이더 각반",
      "server_id": 34,
      "server_name": "리오나04",
      "enchant_level": 5,
      "grade": "legendary",
      "image": "https://wstatic-cdn.plaync.com/powerbook/l2m/icon/Icon_128/Item/Icon_AR_Pants_G2_001.png",
      "now_min_unit_price": 62000,
      "avg_unit_price": 0,
      "favorite": false
    },
    {
      "item_id": 200220001,
      "item_name": "임페리얼 크루세이더 각반",
      "server_id": 56,
      "server_name": "거스틴06",
      "enchant_level": 5,
      "grade": "legendary",
      "image": "https://wstatic-cdn.plaync.com/powerbook/l2m/icon/Icon_128/Item/Icon_AR_Pants_G2_001.png",
      "now_min_unit_price": 65000,
      "avg_unit_price": 0,
      "favorite": false
    },
    {
      "item_id": 200220001,
      "item_name": "임페리얼 크루세이더 각반",
      "server_id": 49,
      "server_name": "에리카09",
      "enchant_level": 5,
      "grade": "legendary",
      "image": "https://wstatic-cdn.plaync.com/powerbook/l2m/icon/Icon_128/Item/Icon_AR_Pants_G2_001.png",
      "now_min_unit_price": 75000,
      "avg_unit_price": 55000,
      "favorite": false
    },
    {
      "item_id": 200220002,
      "item_name": "타락 천사의 각반",
      "server_id": 27,
      "server_name": "카인07",
      "enchant_level": 5,
      "grade": "legendary",
      "image": "https://wstatic-cdn.plaync.com/powerbook/l2m/icon/Icon_128/Item/Icon_AR_Pants_G2_002.png",
      "now_min_unit_price": 169900,
      "avg_unit_price": 170000,
      "favorite": false
    },
    {
      "item_id": 200220002,
      "item_name": "타락 천사의 각반",
      "server_id": 25,
      "server_name": "카인05",
      "enchant_level": 5,
      "grade": "legendary",
      "image": "https://wstatic-cdn.plaync.com/powerbook/l2m/icon/Icon_128/Item/Icon_AR_Pants_G2_002.png",
      "now_min_unit_price": 178987,
      "avg_unit_price": 0,
      "favorite": false
    }
  ],
  "pagination": {
    "page": 9,
    "size": 15,
    "last_page": 20697,
    "total": 310443
  }
}
{
  "contents": [
    {
      "item_id": 200220002,
      "item_name": "타락 천사의 각반",
      "server_id": 105,
      "server_name": "에르휘나05",
      "enchant_level": 5,
      "grade": "legendary",
      "image": "https://wstatic-cdn.plaync.com/powerbook/l2m/icon/Icon_128/Item/Icon_AR_Pants_G2_002.png",
      "now_min_unit_price": 179500,
      "avg_unit_price": 0,
      "favorite": false
    },
    {
      "item_id": 200220002,
      "item_name": "타락 천사의 각반",
      "server_id": 38,
      "server_name": "리오나08",
      "enchant_level": 5,
      "grade": "legendary",
      "image": "https://wstatic-cdn.plaync.com/powerbook/l2m/icon/Icon_128/Item/Icon_AR_Pants_G2_002.png",
      "now_min_unit_price": 185000,
      "avg_unit_price": 0,
      "favorite": false
    },
    {
      "item_id": 200220002,
      "item_name": "타락 천사의 각반",
      "server_id": 108,
      "server_name": "에르휘나08",
      "enchant_level": 5,
      "grade": "legendary",
      "image": "https://wstatic-cdn.plaync.com/powerbook/l2m/icon/Icon_128/Item/Icon_AR_Pants_G2_002.png",
      "now_min_unit_price": 185000,
      "avg_unit_price": 0,
      "favorite": false
    },
    {
      "item_id": 200220002,
      "item_name": "타락 천사의 각반",
      "server_id": 122,
      "server_name": "오필리아02",
      "enchant_level": 5,
      "grade": "legendary",
      "image": "https://wstatic-cdn.plaync.com/powerbook/l2m/icon/Icon_128/Item/Icon_AR_Pants_G2_002.png",
      "now_min_unit_price": 185000,
      "avg_unit_price": 0,
      "favorite": false
    },
    {
      "item_id": 200320001,
      "item_name": "드라코닉 레더 글로브",
      "server_id": 1,
      "server_name": "바츠01",
      "enchant_level": 3,
      "grade": "legendary",
      "image": "https://wstatic-cdn.plaync.com/powerbook/l2m/icon/Icon_128/Item/Icon_AR_Gloves_G2_001.png",
      "now_min_unit_price": 85000,
      "avg_unit_price": 0,
      "favorite": false
    },
    {
      "item_id": 200320001,
      "item_name": "드라코닉 레더 글로브",
      "server_id": 51,
      "server_name": "거스틴01",
      "enchant_level": 5,
      "grade": "legendary",
      "image": "https://wstatic-cdn.plaync.com/powerbook/l2m/icon/Icon_128/Item/Icon_AR_Gloves_G2_001.png",
      "now_min_unit_price": 65000,
      "avg_unit_price": 0,
      "favorite": false
    },
    {
      "item_id": 200320001,
      "item_name": "드라코닉 레더 글로브",
      "server_id": 56,
      "server_name": "거스틴06",
      "enchant_level": 5,
      "grade": "legendary",
      "image": "https://wstatic-cdn.plaync.com/powerbook/l2m/icon/Icon_128/Item/Icon_AR_Gloves_G2_001.png",
      "now_min_unit_price": 70000,
      "avg_unit_price": 0,
      "favorite": false
    },
    {
      "item_id": 200320001,
      "item_name": "드라코닉 레더 글로브",
      "server_id": 31,
      "server_name": "리오나01",
      "enchant_level": 5,
      "grade": "legendary",
      "image": "https://wstatic-cdn.plaync.com/powerbook/l2m/icon/Icon_128/Item/Icon_AR_Gloves_G2_001.png",
      "now_min_unit_price": 80000,
      "avg_unit_price": 0,
      "favorite": false
    },
    {
      "item_id": 200320001,
      "item_name": "드라코닉 레더 글로브",
      "server_id": 108,
      "server_name": "에르휘나08",
      "enchant_level": 5,
      "grade": "legendary",
      "image": "https://wstatic-cdn.plaync.com/powerbook/l2m/icon/Icon_128/Item/Icon_AR_Gloves_G2_001.png",
      "now_min_unit_price": 80000,
      "avg_unit_price": 0,
      "favorite": false
    },
    {
      "item_id": 200320001,
      "item_name": "드라코닉 레더 글로브",
      "server_id": 122,
      "server_name": "오필리아02",
      "enchant_level": 5,
      "grade": "legendary",
      "image": "https://wstatic-cdn.plaync.com/powerbook/l2m/icon/Icon_128/Item/Icon_AR_Gloves_G2_001.png",
      "now_min_unit_price": 84000,
      "avg_unit_price": 0,
      "favorite": false
    },
    {
      "item_id": 200320001,
      "item_name": "드라코닉 레더 글로브",
      "server_id": 39,
      "server_name": "리오나09",
      "enchant_level": 5,
      "grade": "legendary",
      "image": "https://wstatic-cdn.plaync.com/powerbook/l2m/icon/Icon_128/Item/Icon_AR_Gloves_G2_001.png",
      "now_min_unit_price": 85000,
      "avg_unit_price": 0,
      "favorite": false
    },
    {
      "item_id": 200320002,
      "item_name": "파아그리오의 불꽃",
      "server_id": 122,
      "server_name": "오필리아02",
      "enchant_level": 0,
      "grade": "legendary",
      "image": "https://wstatic-cdn.plaync.com/powerbook/l2m/icon/Icon_128/Item/Icon_AR_Gloves_G2_002.png",
      "now_min_unit_price": 77777,
      "avg_unit_price": 0,
      "favorite": false
    },
    {
      "item_id": 200320002,
      "item_name": "파아그리오의 불꽃",
      "server_id": 91,
      "server_name": "테온01",
      "enchant_level": 5,
      "grade": "legendary",
      "image": "https://wstatic-cdn.plaync.com/powerbook/l2m/icon/Icon_128/Item/Icon_AR_Gloves_G2_002.png",
      "now_min_unit_price": 62000,
      "avg_unit_price": 70000,
      "favorite": false
    },
    {
      "item_id": 200320002,
      "item_name": "파아그리오의 불꽃",
      "server_id": 11,
      "server_name": "지그하르트01",
      "enchant_level": 5,
      "grade": "legendary",
      "image": "https://wstatic-cdn.plaync.com/powerbook/l2m/icon/Icon_128/Item/Icon_AR_Gloves_G2_002.png",
      "now_min_unit_price": 68000,
      "avg_unit_price": 0,
      "favorite": false
    },
    {
      "item_id": 200320002,
      "item_name": "파아그리오의 불꽃",
      "server_id": 14,
      "server_name": "지그하르트04",
      "enchant_level": 5,
      "grade": "legendary",
      "image": "https://wstatic-cdn.plaync.com/powerbook/l2m/icon/Icon_128/Item/Icon_AR_Gloves_G2_002.png",
      "now_min_unit_price": 69000,
      "avg_unit_price": 0,
      "favorite": false
    }
  ],
  "pagination": {
    "page": 10,
    "size": 15,
    "last_page": 20697,
    "total": 310442
  }
}
